agentexec/__init__.py
agentexec/config.py
agentexec/pipeline.py
agentexec/tracker.py
agentexec/activity/__init__.py
agentexec/activity/models.py
agentexec/activity/schemas.py
agentexec/activity/tracker.py
agentexec/core/__init__.py
agentexec/core/db.py
agentexec/core/logging.py
agentexec/core/queue.py
agentexec/core/results.py
agentexec/core/task.py
agentexec/runners/__init__.py
agentexec/runners/base.py
agentexec/runners/openai.py
agentexec/state/__init__.py
agentexec/state/backend.py
agentexec/state/redis_backend.py
agentexec/worker/__init__.py
agentexec/worker/event.py
agentexec/worker/logging.py
agentexec/worker/pool.py
agentexec-0.1.5.dist-info/METADATA
agentexec-0.1.5.dist-info/WHEEL
agentexec-0.1.5.dist-info/RECORD
