Metadata-Version: 2.4
Name: agentexec
Version: 0.1.5
Summary: Production-ready orchestration for OpenAI Agents with Redis-backed coordination, activity tracking, and workflow management
Project-URL: Homepage, https://github.com/Agent-CI/agentexec
Project-URL: Documentation, https://github.com/Agent-CI/agentexec#readme
Project-URL: Repository, https://github.com/Agent-CI/agentexec
Project-URL: Issues, https://github.com/Agent-CI/agentexec/issues
Author-email: Agent CI <hello@agent-ci.com>, Travis Dent <root@a10k.co>
License: MIT
Keywords: agents,async,background-workers,openai,orchestration,redis
Classifier: Development Status :: 3 - Alpha
Classifier: Intended Audience :: Developers
Classifier: License :: OSI Approved :: MIT License
Classifier: Programming Language :: Python :: 3
Classifier: Programming Language :: Python :: 3.12
Classifier: Programming Language :: Python :: 3.13
Requires-Python: >=3.12
Requires-Dist: openai-agents>=0.1.0
Requires-Dist: pydantic-settings>=2.5.0
Requires-Dist: pydantic>=2.12.0
Requires-Dist: redis>=7.0.1
Requires-Dist: sqlalchemy>=2.0.44
